MANIFEST.in
README.rst
requirements-install.txt
requirements-test.txt
setup.py
refund_calculation/__init__.py
refund_calculation/events.py
refund_calculation/history.py
refund_calculation/util.py
refund_calculation/windows.py
refund_calculation.egg-info/PKG-INFO
refund_calculation.egg-info/SOURCES.txt
refund_calculation.egg-info/dependency_links.txt
refund_calculation.egg-info/top_level.txt