Metadata-Version: 1.1
Name: refund-calculation
Version: 0.1
Summary: Turns a chronological sequence of balance-adjustment events into a timeline of periods during which particular balances were held.
Home-page: https://github.com/chris-martin/refund-calculation
Author: Chris Martin
Author-email: ch.martin@gmail.com
License: MIT
Platform: UNKNOWN
Classifier: Intended Audience :: Developers
Classifier: License :: OSI Approved :: MIT License
Classifier: Programming Language :: Python
Classifier: Topic :: Software Development :: Libraries :: Python Modules
Classifier: Programming Language :: Python :: 2.7
Classifier: Programming Language :: Python :: 3.3
Classifier: Programming Language :: Python :: 3.4
